JSFetch/__init__.py
JSFetch/errors.py
JSFetch/main.py
JSFetch-0.0.6.dist-info/METADATA
JSFetch-0.0.6.dist-info/WHEEL
JSFetch-0.0.6.dist-info/top_level.txt
JSFetch-0.0.6.dist-info/RECORD
