Metadata-Version: 2.1
Name: JSFetch
Version: 0.0.6
Summary: Lets you make fetch requests in python as you would in JavaScript
Home-page: https://github.com/fschatbot/JSFetch
Author: FSChatBot
License: UNKNOWN
Project-URL: Bug Tracker, https://github.com/fschatbot/JSFetch/issues
Keywords: Networking,Javascript,JS,Fetch,Async,AsyncIO,AsyncHTTPClient,AsyncHTTP
Platform: UNKNOWN
Classifier: Development Status :: 3 - Alpha
Classifier: Intended Audience :: Developers
Classifier: Programming Language :: Python :: 3
Classifier: License :: OSI Approved :: MIT License
Classifier: Operating System :: OS Independent
Requires-Python: >=3.10
Requires-Dist: aiohttp (==3.8.1)
